.coveragerc
.gitignore
.travis.yml
LICENSE.GPL
LICENSE.txt
MANIFEST.in
README.rst
bootstrap.py
buildout.cfg
setup.py
collective/__init__.py
collective.celery.egg-info/PKG-INFO
collective.celery.egg-info/SOURCES.txt
collective.celery.egg-info/dependency_links.txt
collective.celery.egg-info/entry_points.txt
collective.celery.egg-info/namespace_packages.txt
collective.celery.egg-info/not-zip-safe
collective.celery.egg-info/requires.txt
collective.celery.egg-info/top_level.txt
collective/celery/__init__.py
collective/celery/base_task.py
collective/celery/configure.zcml
collective/celery/functionrunner.py
collective/celery/testing.py
collective/celery/utils.py
collective/celery/scripts/__init__.py
collective/celery/scripts/ccelery.py
collective/celery/tests/__init__.py
collective/celery/tests/base.py
collective/celery/tests/test_base_task.py
collective/celery/tests/test_functionrunner.py
collective/celery/tests/test_utils.py
docs/CHANGES.rst
docs/README.rst
docs/conf.py
docs/execution-model.rst
docs/index.rst
docs/tips-and-tricks.rst
docs/using-task-class.rst
docs/api/collective.celery.rst
docs/api/collective.rst
docs/api/modules.rst