Metadata-Version: 2.1
Name: collective.celery
Version: 1.1.0
Summary: Celery for Plone
Home-page: https://github.com/collective/collective.celery
Author: Nathan Van Gheem
Author-email: vangheem@gmail.com
License: GPL
Keywords: celery async plone
Platform: UNKNOWN
Classifier: Programming Language :: Python
Classifier: Framework :: Plone :: 4.0
Classifier: Framework :: Plone :: 4.1
Classifier: Framework :: Plone :: 4.2
Classifier: Framework :: Plone :: 4.3
Classifier: Framework :: Plone :: 5.0
Provides-Extra: test
